kiara_plugin/streamlit/__init__.py
kiara_plugin/streamlit/api.py
kiara_plugin/streamlit/data_types.py
kiara_plugin/streamlit/defaults.py
kiara_plugin/streamlit/models.py
kiara_plugin/streamlit/py.typed
kiara_plugin/streamlit/streamlit.py
kiara_plugin/streamlit/version.txt
kiara_plugin/streamlit/components/__init__.py
kiara_plugin/streamlit/components/models.py
kiara_plugin/streamlit/components/context/__init__.py
kiara_plugin/streamlit/components/data_import/__init__.py
kiara_plugin/streamlit/components/data_import/tabular.py
kiara_plugin/streamlit/components/explore/__init__.py
kiara_plugin/streamlit/components/explore/tabular.py
kiara_plugin/streamlit/components/info/__init__.py
kiara_plugin/streamlit/components/info/api.py
kiara_plugin/streamlit/components/info/components.py
kiara_plugin/streamlit/components/input/__init__.py
kiara_plugin/streamlit/components/input/assemblies.py
kiara_plugin/streamlit/components/input/container_types.py
kiara_plugin/streamlit/components/input/files.py
kiara_plugin/streamlit/components/input/scalars.py
kiara_plugin/streamlit/components/modals/__init__.py
kiara_plugin/streamlit/components/operations/__init__.py
kiara_plugin/streamlit/components/pipelines/__init__.py
kiara_plugin/streamlit/components/preview/__init__.py
kiara_plugin/streamlit/components/preview/assemblies.py
kiara_plugin/streamlit/components/preview/core_types.py
kiara_plugin/streamlit/components/preview/tabular.py
kiara_plugin/streamlit/components/workflow/__init__.py
kiara_plugin/streamlit/components/workflow/dynamic/__init__.py
kiara_plugin/streamlit/components/workflow/dynamic/components.py
kiara_plugin/streamlit/components/workflow/dynamic/workflow_page.py
kiara_plugin/streamlit/components/workflow/requirements/__init__.py
kiara_plugin/streamlit/components/workflow/static/__init__.py
kiara_plugin/streamlit/components/workflow/static/components.py
kiara_plugin/streamlit/components/workflow/static/workflow_page.py
kiara_plugin/streamlit/interfaces/__init__.py
kiara_plugin.streamlit-0.5.1.dist-info/AUTHORS.md
kiara_plugin.streamlit-0.5.1.dist-info/LICENSE
kiara_plugin.streamlit-0.5.1.dist-info/METADATA
kiara_plugin.streamlit-0.5.1.dist-info/WHEEL
kiara_plugin.streamlit-0.5.1.dist-info/entry_points.txt
kiara_plugin.streamlit-0.5.1.dist-info/top_level.txt
kiara_plugin.streamlit-0.5.1.dist-info/RECORD
