Metadata-Version: 2.1
Name: kiara-plugin.streamlit
Version: 0.5.1
Summary: Streamlit UI and widgets for kiara
Author-email: Markus Binsteiner <markus@frkl.io>
License: MPL-2.0
Project-URL: homepage, https://github.com/DHARPA-Project/kiara_plugin.streamlit
Project-URL: documentation, https://DHARPA-Project.github.io/kiara_plugin.streamlit
Project-URL: repository, https://github.com/DHARPA-Project/kiara_plugin.streamlit
Keywords: kiara,streamlit
Classifier: Programming Language :: Python :: 3
Classifier: Development Status :: 3 - Alpha
Classifier: License :: OSI Approved :: Mozilla Public License 2.0 (MPL 2.0)
Classifier: Programming Language :: Python
Classifier: Programming Language :: Python :: 3
Classifier: Programming Language :: Python :: 3 :: Only
Classifier: Programming Language :: Python :: 3.8
Classifier: Programming Language :: Python :: 3.9
Classifier: Programming Language :: Python :: 3.10
Classifier: Programming Language :: Python :: 3.11
Classifier: Programming Language :: Python :: 3.12
Requires-Python: >=3.8
License-File: LICENSE
License-File: AUTHORS.md
Requires-Dist: kiara <0.6.0,>=0.5.4
Requires-Dist: kiara-plugin.tabular <0.6.0,>=0.5.0
Requires-Dist: kiara-plugin.onboarding <0.6.0,>=0.5.0
Requires-Dist: kiara-plugin.html <0.6.0,>=0.5.0
Requires-Dist: streamlit >=1.24.0
Requires-Dist: streamlit-aggrid >=0.3.4
Requires-Dist: streamlit-option-menu >=0.3.6
Requires-Dist: importlib-resources
Requires-Dist: pydot >=1.4.0
Requires-Dist: pygwalker >=0.1.11
Requires-Dist: streamlit-scrollable-textbox >=0.0.3
Requires-Dist: streamlit-tags >=1.2.8
Provides-Extra: all_plugins
Requires-Dist: kiara-plugin.network-analysis >=0.4.14 ; extra == 'all_plugins'
Requires-Dist: kiara-plugin.language-processing >=0.4.10 ; extra == 'all_plugins'
Provides-Extra: dev_all
Requires-Dist: kiara[dev_all] ; extra == 'dev_all'
Provides-Extra: dev_documentation
Requires-Dist: kiara[dev_documentation] ; extra == 'dev_documentation'
Provides-Extra: dev_testing
Requires-Dist: kiara[dev_testing] ; extra == 'dev_testing'
Requires-Dist: kiara-plugin.network-analysis >=0.4.7 ; extra == 'dev_testing'
Provides-Extra: dev_utils
Requires-Dist: kiara[dev_utils] ; extra == 'dev_utils'
Provides-Extra: streamlit
Requires-Dist: kiara-plugin.streamlit ; extra == 'streamlit'
Provides-Extra: workflow_app
Requires-Dist: PyGithub >=1.58.0 ; extra == 'workflow_app'
Requires-Dist: githublfs >=0.1.3 ; extra == 'workflow_app'
